tests/__init__.py
tests/test_exceptions.py
tests/test_fields.py
tests/test_list.py
tests/test_schema.py
wattle/__init__.py
wattle/exceptions.py
wattle/nodes.py
wattle/schema.py
woning_wattle-0.4.1.dist-info/METADATA
woning_wattle-0.4.1.dist-info/RECORD
woning_wattle-0.4.1.dist-info/WHEEL
woning_wattle-0.4.1.dist-info/top_level.txt
