Metadata-Version: 2.1
Name: woning-wattle
Version: 0.4.1
Summary: Library for converting yaml structures to Python objects, based on a predefined object hierarchy schema.
Home-page: https://gitlab.com/woning-group/libs/wattle
License: UNKNOWN
Platform: UNKNOWN
Requires-Dist: pyyaml
